Package_mkm77/__init__.py
Package_mkm77-0.1.dist-info/METADATA
Package_mkm77-0.1.dist-info/WHEEL
Package_mkm77-0.1.dist-info/top_level.txt
Package_mkm77-0.1.dist-info/RECORD
