Metadata-Version: 2.1
Name: Package_mkm77
Version: 0.1
Summary: A basic mathematical operation package
Author: Mukesh
Keywords: python,maths
Classifier: Development Status :: 1 - Planning
Classifier: Intended Audience :: Developers
Classifier: Programming Language :: Python :: 3
Classifier: Operating System :: Unix
Classifier: Operating System :: MacOS :: MacOS X
Classifier: Operating System :: Microsoft :: Windows
